[
  {
    "title": "HTML",
    "imageSrc": "skills/html.png"
  },
  {
    "title": "CSS",
    "imageSrc": "skills/css.png"
  },
  {
    "title": "React",
    "imageSrc": "skills/react.png"
  },
  {
    "title": "Node",
    "imageSrc": "skills/node.png"
  },
  {
    "title": "Python",
    "imageSrc": "skills/python.png"
  },
  {
    "title": "R",
    "imageSrc": "skills/R.png"
  },
  {
    "title": "Java",
    "imageSrc": "skills/java.png"
  },
  {
    "title": "Github",
    "imageSrc": "skills/github.png"
  },
  {
    "title": "Tensorflow",
    "imageSrc": "skills/tensorflow.png"
  }

]
